connectwise_client/main.py
connectwise_client-1.0.2.dist-info/LICENSE
connectwise_client-1.0.2.dist-info/METADATA
connectwise_client-1.0.2.dist-info/WHEEL
connectwise_client-1.0.2.dist-info/top_level.txt
connectwise_client-1.0.2.dist-info/RECORD
