Metadata-Version: 2.1
Name: connectwise-client
Version: 1.0.2
Summary: Project to download data from Connectwise using the api client.
Author-email: Papa Bear Codes Python <papa.bear.codes.python@gmail.com>
License: Apache License
Project-URL: homepage, https://github.com/papabearcodespython/connectwise_client
Project-URL: documentation, https://github.com/papabearcodespython/connectwise_client/blob/main/README.md
Project-URL: repository, https://github.com/papabearcodespython/connectwise_client.git
Project-URL: changelog, https://github.com/papabearcodespython/connectwise_client/blob/main/CHANGELOG.md
Keywords: connectwise,api client
Requires-Python: >=3.11
License-File: LICENSE
Requires-Dist: certifi ==2023.7.22
Requires-Dist: charset-normalizer ==3.2.0
Requires-Dist: idna ==3.4
Requires-Dist: numpy ==1.25.2
Requires-Dist: pandas ==2.0.3
Requires-Dist: python-dateutil ==2.8.2
Requires-Dist: pytz ==2023.3
Requires-Dist: requests ==2.31.0
Requires-Dist: six ==1.16.0
Requires-Dist: tzdata ==2023.3
Requires-Dist: urllib3 ==2.0.4
Provides-Extra: development
Requires-Dist: astroid ==2.15.6 ; extra == 'development'
Requires-Dist: black ==23.7.0 ; extra == 'development'
Requires-Dist: build ==0.10.0 ; extra == 'development'
Requires-Dist: click ==8.1.6 ; extra == 'development'
Requires-Dist: coverage[toml] ==7.2.7 ; extra == 'development'
Requires-Dist: dill ==0.3.7 ; extra == 'development'
Requires-Dist: iniconfig ==2.0.0 ; extra == 'development'
Requires-Dist: isort ==5.12.0 ; extra == 'development'
Requires-Dist: lazy-object-proxy ==1.9.0 ; extra == 'development'
Requires-Dist: mccabe ==0.7.0 ; extra == 'development'
Requires-Dist: mypy ==1.4.1 ; extra == 'development'
Requires-Dist: mypy-extensions ==1.0.0 ; extra == 'development'
Requires-Dist: packaging ==23.1 ; extra == 'development'
Requires-Dist: pathspec ==0.11.2 ; extra == 'development'
Requires-Dist: pip-tools ==7.3.0 ; extra == 'development'
Requires-Dist: pipdeptree ==2.12.0 ; extra == 'development'
Requires-Dist: platformdirs ==3.10.0 ; extra == 'development'
Requires-Dist: pluggy ==1.2.0 ; extra == 'development'
Requires-Dist: pydocstyle ==6.3.0 ; extra == 'development'
Requires-Dist: pylint ==2.17.5 ; extra == 'development'
Requires-Dist: pyproject-hooks ==1.0.0 ; extra == 'development'
Requires-Dist: pytest ==7.4.0 ; extra == 'development'
Requires-Dist: pytest-cov ==4.1.0 ; extra == 'development'
Requires-Dist: setuptools-scm ==7.1.0 ; extra == 'development'
Requires-Dist: snowballstemmer ==2.2.0 ; extra == 'development'
Requires-Dist: toml ==0.10.2 ; extra == 'development'
Requires-Dist: tomlkit ==0.12.1 ; extra == 'development'
Requires-Dist: typing-extensions ==4.7.1 ; extra == 'development'
Requires-Dist: update-toml ==0.0.3 ; extra == 'development'
Requires-Dist: wheel ==0.41.1 ; extra == 'development'
Requires-Dist: wrapt ==1.15.0 ; extra == 'development'
Requires-Dist: pip ==23.2.1 ; extra == 'development'
Requires-Dist: setuptools ==68.0.0 ; extra == 'development'
